subreader/__init__.py
subreader/file_ops.py
subreader/read_ass.py
subreader/read_srt.py
subreader-0.0.1.dist-info/licenses/LICENSE
subreader-0.0.1.dist-info/METADATA
subreader-0.0.1.dist-info/WHEEL
subreader-0.0.1.dist-info/top_level.txt
subreader-0.0.1.dist-info/RECORD
