Metadata-Version: 2.4
Name: subreader
Version: 0.0.1
Summary: read srt, ass files
Home-page: https://github.com/xinglufan/subreader
Author: aipiecool
Author-email: aipiecool@example.com
Classifier: Programming Language :: Python :: 3
Classifier: License :: OSI Approved :: Apache Software License
Classifier: Operating System :: OS Independent
Requires-Python: >=3.7
License-File: LICENSE
Requires-Dist: apnode>=0.0.1
Requires-Dist: ass>=0.5.4
Requires-Dist: chardet>=5.2.0
Dynamic: author
Dynamic: author-email
Dynamic: classifier
Dynamic: description
Dynamic: description-content-type
Dynamic: home-page
Dynamic: license-file
Dynamic: requires-dist
Dynamic: requires-python
Dynamic: summary
